{
  "item": [
    {
      "guideparam": [],
      "guidetype": 0,
      "id": 1
    },
    {
      "guideparam": [
        "guide_1",
        "guide_2",
        "guide_3",
        "guide_4",
        "guide_5",
        "guide_6"
      ],
      "guidetype": 0,
      "id": 2
    },
    {
      "guideparam": [
        "guide_7",
        "guide_56",
        "guide_8",
        "guide_9"
      ],
      "guidetype": 0,
      "id": 3
    },
    {
      "guideparam": [],
      "guidetype": 0,
      "id": 4
    },
    {
      "guideparam": [],
      "guidetype": 0,
      "id": 5
    },
    {
      "guideparam": [
        "guide_10",
        "guide_11",
        "guide_12"
      ],
      "guidetype": 0,
      "id": 6
    },
    {
      "guideparam": [
        "guide_10",
        "guide_13",
        "guide_14",
        "guide_15"
      ],
      "guidetype": 0,
      "id": 7
    },
    {
      "guideparam": [
        "guide_10",
        "guide_11",
        "guide_16",
        "guide_17"
      ],
      "guidetype": 0,
      "id": 8
    },
    {
      "guideparam": [],
      "guidetype": 0,
      "id": 9
    },
    {
      "guideparam": [],
      "guidetype": 0,
      "id": 10
    },
    {
      "guideparam": [],
      "guidetype": 0,
      "id": 11
    },
    {
      "guideparam": [],
      "guidetype": 0,
      "id": 12
    },
    {
      "guideparam": [],
      "guidetype": 0,
      "id": 13
    },
    {
      "guideparam": [
        "guide_10",
        "guide_18",
        "guide_19"
      ],
      "guidetype": 0,
      "id": 14
    },
    {
      "guideparam": [],
      "guidetype": 0,
      "id": 15
    },
    {
      "guideparam": [],
      "guidetype": 0,
      "id": 16
    },
    {
      "guideparam": [],
      "guidetype": 0,
      "id": 17
    },
    {
      "guideparam": [],
      "guidetype": 0,
      "id": 18
    },
    {
      "guideparam": [],
      "guidetype": 0,
      "id": 19
    },
    {
      "guideparam": [
        "低",
        "1天",
        "几米"
      ],
      "guidetype": 0,
      "id": 20
    },
    {
      "guideparam": [],
      "guidetype": 0,
      "id": 21
    },
    {
      "guideparam": [
        "guide_10",
        "guide_22",
        "guide_23"
      ],
      "guidetype": 0,
      "id": 22
    },
    {
      "guideparam": [
        "guide_24",
        "guide_25",
        "guide_26"
      ],
      "guidetype": 0,
      "id": 23
    },
    {
      "guideparam": [
        "guide_10",
        "guide_27",
        "guide_28"
      ],
      "guidetype": 0,
      "id": 24
    },
    {
      "guideparam": [
        "低",
        "1天",
        "几米"
      ],
      "guidetype": 0,
      "id": 25
    },
    {
      "guideparam": [],
      "guidetype": 0,
      "id": 26
    },
    {
      "guideparam": [],
      "guidetype": 0,
      "id": 27
    },
    {
      "guideparam": [],
      "guidetype": 0,
      "id": 28
    },
    {
      "guideparam": [
        "guide_10",
        "guide_22",
        "guide_29"
      ],
      "guidetype": 0,
      "id": 29
    },
    {
      "guideparam": [],
      "guidetype": 0,
      "id": 30
    },
    {
      "guideparam": [
        "guide_10",
        "guide_27",
        "guide_30",
        "guide_31"
      ],
      "guidetype": 0,
      "id": 31
    },
    {
      "guideparam": [],
      "guidetype": 0,
      "id": 32
    },
    {
      "guideparam": [],
      "guidetype": 0,
      "id": 33
    },
    {
      "guideparam": [],
      "guidetype": 0,
      "id": 34
    },
    {
      "guideparam": [],
      "guidetype": 0,
      "id": 35
    },
    {
      "guideparam": [],
      "guidetype": 0,
      "id": 36
    },
    {
      "guideparam": [],
      "guidetype": 0,
      "id": 37
    },
    {
      "guideparam": [
        "guide_34",
        "guide_35",
        "guide_36"
      ],
      "guidetype": 0,
      "id": 38
    },
    {
      "guideparam": [
        "guide_37",
        "guide_38"
      ],
      "guidetype": 0,
      "id": 39
    },
    {
      "guideparam": [],
      "guidetype": 0,
      "id": 40
    },
    {
      "guideparam": [
        "低",
        "1天",
        "几米"
      ],
      "guidetype": 0,
      "id": 41
    },
    {
      "guideparam": [
        "guide_39"
      ],
      "guidetype": 0,
      "id": 42
    },
    {
      "guideparam": [],
      "guidetype": 0,
      "id": 43
    },
    {
      "guideparam": [],
      "guidetype": 0,
      "id": 44
    },
    {
      "guideparam": [],
      "guidetype": 0,
      "id": 45
    },
    {
      "guideparam": [],
      "guidetype": 0,
      "id": 46
    },
    {
      "guideparam": [
        "低",
        "1天",
        "几米"
      ],
      "guidetype": 0,
      "id": 47
    },
    {
      "guideparam": [],
      "guidetype": 0,
      "id": 48
    },
    {
      "guideparam": [],
      "guidetype": 0,
      "id": 49
    },
    {
      "guideparam": [
        "guide_32",
        "guide_33",
        "guide_40",
        "guide_41",
        "guide_42"
      ],
      "guidetype": 0,
      "id": 50
    },
    {
      "guideparam": [
        "guide_32",
        "guide_20",
        "guide_21",
        "guide_43"
      ],
      "guidetype": 0,
      "id": 51
    },
    {
      "guideparam": [
        "guide_32",
        "guide_20",
        "guide_21",
        "guide_44"
      ],
      "guidetype": 0,
      "id": 52
    },
    {
      "guideparam": [],
      "guidetype": 0,
      "id": 53
    },
    {
      "guideparam": [],
      "guidetype": 0,
      "id": 54
    },
    {
      "guideparam": [],
      "guidetype": 0,
      "id": 55
    },
    {
      "guideparam": [],
      "guidetype": 0,
      "id": 56
    },
    {
      "guideparam": [
        "低",
        "1天",
        "几米"
      ],
      "guidetype": 0,
      "id": 57
    },
    {
      "guideparam": [
        "低",
        "1天",
        "几米"
      ],
      "guidetype": 0,
      "id": 58
    },
    {
      "guideparam": [
        "guide_45",
        "guide_46"
      ],
      "guidetype": 0,
      "id": 59
    },
    {
      "guideparam": [],
      "guidetype": 0,
      "id": 60
    },
    {
      "guideparam": [
        "低",
        "5-7天",
        "几米"
      ],
      "guidetype": 0,
      "id": 61
    },
    {
      "guideparam": [
        "低",
        "5-7天",
        "几米"
      ],
      "guidetype": 0,
      "id": 62
    },
    {
      "guideparam": [],
      "guidetype": 0,
      "id": 63
    },
    {
      "guideparam": [],
      "guidetype": 0,
      "id": 64
    },
    {
      "guideparam": [],
      "guidetype": 0,
      "id": 65
    },
    {
      "guideparam": [],
      "guidetype": 0,
      "id": 66
    },
    {
      "guideparam": [],
      "guidetype": 0,
      "id": 67
    },
    {
      "guideparam": [],
      "guidetype": 0,
      "id": 68
    },
    {
      "guideparam": [],
      "guidetype": 0,
      "id": 69
    },
    {
      "guideparam": [],
      "guidetype": 0,
      "id": 70
    },
    {
      "guideparam": [
        "guide_32",
        "guide_47",
        "guide_48",
        "guide_49"
      ],
      "guidetype": 0,
      "id": 71
    },
    {
      "guideparam": [
        "低",
        "1天",
        "艾欧丽娅"
      ],
      "guidetype": 0,
      "id": 72
    },
    {
      "guideparam": [],
      "guidetype": 0,
      "id": 73
    },
    {
      "guideparam": [],
      "guidetype": 0,
      "id": 74
    },
    {
      "guideparam": [],
      "guidetype": 0,
      "id": 75
    },
    {
      "guideparam": [],
      "guidetype": 0,
      "id": 76
    },
    {
      "guideparam": [
        "低",
        "2-3天",
        "几米"
      ],
      "guidetype": 0,
      "id": 77
    },
    {
      "guideparam": [
        "低",
        "3-4天",
        "几米"
      ],
      "guidetype": 0,
      "id": 78
    },
    {
      "guideparam": [
        "低",
        "3-4天",
        "几米"
      ],
      "guidetype": 0,
      "id": 79
    },
    {
      "guideparam": [
        "低",
        "3-4天",
        "几米"
      ],
      "guidetype": 0,
      "id": 80
    },
    {
      "guideparam": [],
      "guidetype": 0,
      "id": 81
    },
    {
      "guideparam": [],
      "guidetype": 0,
      "id": 82
    },
    {
      "guideparam": [
        "较低",
        "10-12天",
        "艾欧丽娅"
      ],
      "guidetype": 0,
      "id": 83
    },
    {
      "guideparam": [
        "较低",
        "2天",
        "幻境界皇、艾莫莉萨"
      ],
      "guidetype": 0,
      "id": 84
    },
    {
      "guideparam": [],
      "guidetype": 0,
      "id": 85
    },
    {
      "guideparam": [],
      "guidetype": 0,
      "id": 86
    },
    {
      "guideparam": [],
      "guidetype": 0,
      "id": 87
    },
    {
      "guideparam": [
        "较低",
        "3-5天",
        "艾欧丽娅、幻境界皇"
      ],
      "guidetype": 0,
      "id": 88
    },
    {
      "guideparam": [],
      "guidetype": 0,
      "id": 89
    },
    {
      "guideparam": [
        "较低",
        "1天",
        "艾欧丽娅"
      ],
      "guidetype": 0,
      "id": 90
    },
    {
      "guideparam": [
        "较低",
        "4-10天",
        "艾欧丽娅"
      ],
      "guidetype": 0,
      "id": 91
    },
    {
      "guideparam": [
        "较低",
        "10-12天",
        "艾欧丽娅"
      ],
      "guidetype": 0,
      "id": 92
    },
    {
      "guideparam": [
        "guide_54",
        "guide_55"
      ],
      "guidetype": 0,
      "id": 93
    },
    {
      "guideparam": [],
      "guidetype": 0,
      "id": 94
    },
    {
      "guideparam": [],
      "guidetype": 0,
      "id": 95
    },
    {
      "guideparam": [],
      "guidetype": 0,
      "id": 96
    },
    {
      "guideparam": [
        "中",
        "5-7天",
        "幻境界皇"
      ],
      "guidetype": 0,
      "id": 97
    },
    {
      "guideparam": [
        "中",
        "2天",
        "阿徒、5只特性为带电或阴森的精灵"
      ],
      "guidetype": 0,
      "id": 98
    },
    {
      "guideparam": [
        "中",
        "7天",
        "艾欧丽娅、幻境界皇"
      ],
      "guidetype": 0,
      "id": 99
    },
    {
      "guideparam": [
        "中",
        "5-7天",
        "艾欧丽娅、幻境界皇"
      ],
      "guidetype": 0,
      "id": 100
    },
    {
      "guideparam": [],
      "guidetype": 0,
      "id": 101
    },
    {
      "guideparam": [],
      "guidetype": 0,
      "id": 102
    },
    {
      "guideparam": [
        "较难",
        "7天",
        "艾欧丽娅、幻境界皇、王之哈莫"
      ],
      "guidetype": 0,
      "id": 103
    },
    {
      "guideparam": [],
      "guidetype": 0,
      "id": 104
    },
    {
      "guideparam": [
        "guide_50",
        "guide_51"
      ],
      "guidetype": 0,
      "id": 105
    },
    {
      "guideparam": [],
      "guidetype": 0,
      "id": 106
    },
    {
      "guideparam": [],
      "guidetype": 0,
      "id": 107
    },
    {
      "guideparam": [],
      "guidetype": 0,
      "id": 108
    },
    {
      "guideparam": [],
      "guidetype": 0,
      "id": 109
    },
    {
      "guideparam": [],
      "guidetype": 0,
      "id": 110
    },
    {
      "guideparam": [],
      "guidetype": 0,
      "id": 111
    },
    {
      "guideparam": [],
      "guidetype": 0,
      "id": 112
    },
    {
      "guideparam": [
        "较难",
        "7天",
        "艾欧丽娅、幻境界皇、王之哈莫、千裳"
      ],
      "guidetype": 0,
      "id": 113
    },
    {
      "guideparam": [
        "较难",
        "7天",
        "艾欧丽娅、幻境界皇、王之哈莫、千裳"
      ],
      "guidetype": 0,
      "id": 114
    },
    {
      "guideparam": [
        "非常难",
        "暂无有效信息",
        "暂无有效信息"
      ],
      "guidetype": 0,
      "id": 115
    },
    {
      "guideparam": [
        "非常难",
        "暂无有效信息",
        "暂无有效信息"
      ],
      "guidetype": 0,
      "id": 116
    }
  ]
}