{
  "item": [
    {
      "days": 1,
      "fiexdreward1": [
        1,
        1400154,
        20,
        1,
        300675,
        2,
        1,
        300676,
        2,
        1,
        300021,
        5
      ],
      "fiexdreward2": [],
      "id": 101,
      "intro1": "多维度助力精灵养成",
      "intro2": "",
      "judgepet": [],
      "jump1": 0,
      "jump2": 0,
      "name1": "养成好礼",
      "name2": "",
      "optreward1": [],
      "optreward2": []
    },
    {
      "days": 2,
      "fiexdreward1": [
        1,
        300063,
        3,
        1,
        300065,
        3
      ],
      "fiexdreward2": [
        1,
        300063,
        3,
        1,
        300065,
        3
      ],
      "id": 102,
      "intro1": "PVE强力伙伴获取加速",
      "intro2": "旧时伙伴陪伴前行",
      "judgepet": [
        4647,
        6134,
        37380,
        0,
        4648,
        6135,
        37381,
        0,
        4649,
        6136,
        37382,
        0,
        4731,
        6235,
        37814,
        0
      ],
      "jump1": 0,
      "jump2": 111800,
      "name1": "皮神/三主宠道具任选",
      "name2": "精灵任选",
      "optreward1": [
        1,
        1726208,
        1200,
        1,
        1726848,
        200
      ],
      "optreward2": [
        1,
        1727070,
        10,
        4,
        3889,
        1,
        4,
        3890,
        1,
        4,
        3891,
        1
      ]
    },
    {
      "days": 3,
      "fiexdreward1": [
        1,
        1723167,
        3,
        1,
        1723255,
        3
      ],
      "fiexdreward2": [],
      "id": 103,
      "intro1": "精灵和刻印珍贵抽奖道具",
      "intro2": "",
      "judgepet": [],
      "jump1": 0,
      "jump2": 0,
      "name1": "惊喜好礼",
      "name2": "",
      "optreward1": [],
      "optreward2": []
    },
    {
      "days": 4,
      "fiexdreward1": [
        1,
        1706926,
        3,
        1,
        1706826,
        3
      ],
      "fiexdreward2": [
        1,
        1706926,
        3,
        1,
        1706826,
        3
      ],
      "id": 104,
      "intro1": "PVE强力伙伴获取加速",
      "intro2": "旧时伙伴陪伴前行",
      "judgepet": [
        4647,
        6134,
        37380,
        0,
        4648,
        6135,
        37381,
        0,
        4649,
        6136,
        37382,
        0,
        4731,
        6235,
        37814,
        0
      ],
      "jump1": 0,
      "jump2": 111800,
      "name1": "皮神/三主宠道具任选",
      "name2": "精灵任选",
      "optreward1": [
        1,
        1726208,
        1200,
        1,
        1726848,
        200
      ],
      "optreward2": [
        1,
        1727070,
        10,
        4,
        3889,
        1,
        4,
        3890,
        1,
        4,
        3891,
        1
      ]
    },
    {
      "days": 5,
      "fiexdreward1": [
        2,
        40646,
        1,
        2,
        40647,
        1
      ],
      "fiexdreward2": [],
      "id": 105,
      "intro1": "强力刻印助力属性增长",
      "intro2": "",
      "judgepet": [],
      "jump1": 0,
      "jump2": 0,
      "name1": "精灵王系列刻印",
      "name2": "",
      "optreward1": [],
      "optreward2": []
    },
    {
      "days": 6,
      "fiexdreward1": [
        1,
        1706925,
        3,
        1,
        1706928,
        300,
        1,
        1706927,
        300
      ],
      "fiexdreward2": [],
      "id": 106,
      "intro1": "抗性养成必备道具",
      "intro2": "",
      "judgepet": [],
      "jump1": 0,
      "jump2": 0,
      "name1": "宽恕神石组合",
      "name2": "",
      "optreward1": [],
      "optreward2": []
    },
    {
      "days": 7,
      "fiexdreward1": [
        1,
        300066,
        1,
        1,
        1200444,
        10,
        1,
        300784,
        3,
        1,
        300785,
        3
      ],
      "fiexdreward2": [],
      "id": 107,
      "intro1": "精灵刻印珍贵道具",
      "intro2": "",
      "judgepet": [],
      "jump1": 0,
      "jump2": 0,
      "name1": "通用刻印激活水晶",
      "name2": "",
      "optreward1": [],
      "optreward2": []
    },
    {
      "days": 1,
      "fiexdreward1": [
        1,
        1400154,
        20,
        1,
        300675,
        4,
        1,
        300676,
        4,
        1,
        300617,
        5
      ],
      "fiexdreward2": [],
      "id": 201,
      "intro1": "多维度助力精灵养成",
      "intro2": "",
      "judgepet": [],
      "jump1": 0,
      "jump2": 0,
      "name1": "养成好礼",
      "name2": "",
      "optreward1": [],
      "optreward2": []
    },
    {
      "days": 2,
      "fiexdreward1": [
        1,
        300063,
        5,
        1,
        300065,
        5
      ],
      "fiexdreward2": [
        1,
        300063,
        5,
        1,
        300065,
        5
      ],
      "id": 202,
      "intro1": "PVE强力伙伴获取加速",
      "intro2": "旧时伙伴陪伴前行",
      "judgepet": [
        4647,
        6134,
        37380,
        0,
        4648,
        6135,
        37381,
        0,
        4649,
        6136,
        37382,
        0,
        4731,
        6235,
        37814,
        0
      ],
      "jump1": 0,
      "jump2": 111800,
      "name1": "皮神/三主宠道具任选",
      "name2": "精灵任选",
      "optreward1": [
        1,
        1726208,
        1200,
        1,
        1726848,
        200
      ],
      "optreward2": [
        1,
        1727070,
        20,
        4,
        3889,
        1,
        4,
        3890,
        1,
        4,
        3891,
        1
      ]
    },
    {
      "days": 3,
      "fiexdreward1": [
        1,
        1723167,
        5,
        1,
        1723255,
        5
      ],
      "fiexdreward2": [],
      "id": 203,
      "intro1": "精灵和刻印珍贵抽奖道具",
      "intro2": "",
      "judgepet": [],
      "jump1": 0,
      "jump2": 0,
      "name1": "惊喜好礼",
      "name2": "",
      "optreward1": [],
      "optreward2": []
    },
    {
      "days": 4,
      "fiexdreward1": [
        1,
        1706926,
        5,
        1,
        1706826,
        5
      ],
      "fiexdreward2": [
        1,
        1706926,
        5,
        1,
        1706826,
        5
      ],
      "id": 204,
      "intro1": "PVE强力伙伴获取加速",
      "intro2": "旧时伙伴陪伴前行",
      "judgepet": [
        4647,
        6134,
        37380,
        0,
        4648,
        6135,
        37381,
        0,
        4649,
        6136,
        37382,
        0,
        4731,
        6235,
        37814,
        0
      ],
      "jump1": 0,
      "jump2": 111800,
      "name1": "皮神/三主宠道具任选",
      "name2": "精灵任选",
      "optreward1": [
        1,
        1726208,
        1200,
        1,
        1726848,
        200
      ],
      "optreward2": [
        1,
        1727070,
        20,
        4,
        3889,
        1,
        4,
        3890,
        1,
        4,
        3891,
        1
      ]
    },
    {
      "days": 5,
      "fiexdreward1": [
        2,
        40646,
        1,
        2,
        40647,
        1,
        2,
        41078,
        1,
        2,
        40650,
        1
      ],
      "fiexdreward2": [],
      "id": 205,
      "intro1": "强力刻印助力属性增长",
      "intro2": "",
      "judgepet": [],
      "jump1": 0,
      "jump2": 0,
      "name1": "精灵王系列刻印",
      "name2": "",
      "optreward1": [],
      "optreward2": []
    },
    {
      "days": 6,
      "fiexdreward1": [
        1,
        1706925,
        5,
        1,
        1706928,
        500,
        1,
        1706927,
        500
      ],
      "fiexdreward2": [],
      "id": 206,
      "intro1": "抗性养成必备道具",
      "intro2": "",
      "judgepet": [],
      "jump1": 0,
      "jump2": 0,
      "name1": "宽恕神石组合",
      "name2": "",
      "optreward1": [],
      "optreward2": []
    },
    {
      "days": 7,
      "fiexdreward1": [
        1,
        300066,
        2,
        1,
        1200445,
        10,
        1,
        300784,
        5,
        1,
        300785,
        5
      ],
      "fiexdreward2": [],
      "id": 207,
      "intro1": "精灵刻印珍贵道具",
      "intro2": "",
      "judgepet": [],
      "jump1": 0,
      "jump2": 0,
      "name1": "通用刻印激活水晶",
      "name2": "",
      "optreward1": [],
      "optreward2": []
    }
  ]
}